LICENSE
MANIFEST.in
README.md
setup.cfg
setup.py
unidic/__init__.py
unidic/__main__.py
unidic/download.py
unidic/unidic.py
unidic.egg-info/PKG-INFO
unidic.egg-info/SOURCES.txt
unidic.egg-info/dependency_links.txt
unidic.egg-info/requires.txt
unidic.egg-info/top_level.txt