Metadata-Version: 2.1
Name: unidic
Version: 1.0.3
Summary: UniDic packaged for Python
Home-page: https://github.com/polm/unidic-py
Author: Paul O'Leary McCann
Author-email: polm@dampfkraft.com
License: MIT
Platform: UNKNOWN
Classifier: License :: OSI Approved :: MIT License
Classifier: Natural Language :: Japanese
Requires-Python: >=3.5
